or16/or16.vhd
library ieee;
use ieee.std_logic_1164.all;

entity or16 is
    port(
	    A, B : in std_logic_vector(15 downto 0);
	    O    : out std_logic_vector(15 downto 0)
	);
end or16;


architecture rtl of or16 is
begin
    O <= A or B;
end rtl;

or16/or16_tb.vhd
library ieee;
use ieee.std_logic_1164.all;

entity or16_tb is
end or16_tb;

architecture rtl of or16_tb is
    signal A, B : std_logic_vector(15 downto 0);
    signal O    : std_logic_vector(15 downto 0);
    
    component or16 is
	port(
		signal A, B : in std_logic_vector(15 downto 0);
    		signal O    : out std_logic_vector(15 downto 0)
	    );
    end component;
begin
    uut : or16 port map( A => A, B => B, O => O);
    
    stim_proc : process
    begin
        A <= (others => '0');
        B <= (others => '0');
	wait for 10 ns;
        B <= (others => '1');
        wait for 10 ns;
        A <= (others => '1');
        wait for 10 ns;
        B(0) <= '0';
        wait for 10 ns;
        B(0) <= '1';
        B(1) <= '0';
        wait for 10 ns;
        B(1) <= '1';
        B(15) <= '0';
        wait for 10 ns;
        A(0) <= '0';
	B(0) <= '0';
        wait for 10 ns;
	A(15) <='0';
        wait;
    end process;
end rtl;

or16/or16.vcd
$date
  Mon Jun 16 20:51:08 2025
$end
$version
  GHDL v0
$end
$timescale
  1 fs
$end
$scope module standard $end
$upscope $end
$scope module std_logic_1164 $end
$upscope $end
$scope module or16_tb $end
$var reg 16 ! a[15:0] $end
$var reg 16 " b[15:0] $end
$var reg 16 # o[15:0] $end
$scope module uut $end
$var reg 16 $ a[15:0] $end
$var reg 16 % b[15:0] $end
$var reg 16 & o[15:0] $end
$upscope $end
$upscope $end
$enddefinitions $end
#0
b0000000000000000 !
b0000000000000000 "
b0000000000000000 #
b0000000000000000 $
b0000000000000000 %
b0000000000000000 &
#10000000
b1111111111111111 "
b1111111111111111 #
b1111111111111111 %
b1111111111111111 &
#20000000
b1111111111111111 !
b1111111111111111 $
#30000000
b1111111111111110 "
b1111111111111110 %
#40000000
b1111111111111101 "
b1111111111111101 %
#50000000
b0111111111111111 "
b0111111111111111 %
#60000000
b1111111111111110 !
b0111111111111110 "
b1111111111111110 #
b1111111111111110 $
b0111111111111110 %
b1111111111111110 &
#70000000
b0111111111111110 !
b0111111111111110 #
b0111111111111110 $
b0111111111111110 &
